pyvat/SignalGenerator.py
pyvat/Socket_Func.py
pyvat/__init__.py
pyvat/__main__.py
pyvat/compat.py
pyvat/db_opr.py
pyvat/py_na_opr.py
pyvat/py_sa_opr.py
pyvat/ratb5.py
pyvat/vatbase.py
ZITPyVAT-1.0.20.dist-info/METADATA
ZITPyVAT-1.0.20.dist-info/WHEEL
ZITPyVAT-1.0.20.dist-info/top_level.txt
ZITPyVAT-1.0.20.dist-info/RECORD
