Metadata-Version: 2.1
Name: ZITPyVAT
Version: 1.0.20
Summary: ZIT python vat common packages
Home-page: http://www.tjzit.com/
Author: Liugang
Author-email: liugang@gosusncn.com
Maintainer: Liugang
Maintainer-email: liugang@gosusncn.com
License: None
Platform: UNKNOWN
Classifier: Programming Language :: Python
Classifier: Programming Language :: Python :: Implementation
Classifier: Programming Language :: Python :: 2.7
Classifier: Programming Language :: Python :: 3.6
Classifier: Programming Language :: Python :: 3.7
Requires-Dist: PyVISA (==1.10.1)
Requires-Dist: PyVISA-py (==0.4.1)
